{
  "basics": {
    "name": "Megan Yamamoto",
    "label": "Student",
    "picture": "https://MeganYamamoto.github.io/images/CoverPhotoMeganY.jpg",
    "email": "meganhy8@hawaii.edu",
    "phone": "",
    "website": "https://meganyamamoto.github.io",
    "summary": "I am studying for a B.S. in Management Information Systems in the Department of Shidler Business at the University of Hawaii. I expect to graduate in Fall, 2024.",
    "location": {
      "address": "",
      "postalCode": "96789",
      "city": "Mililani",
      "countryCode": "USA",
      "region": "Hawaii"
    },
    "profiles": [
      {
        "network": "github",
        "username": "meganyamamoto",
        "url": "https://github.com/MeganYamamoto"
      },
      {
        "network": "",
        "username": "",
        "url": ""
      },
      {
        "network": "",
        "username": "",
        "url": ""
      },
      {
        "network": "",
        "username": "",
        "url": ""
      }
    ]
  },
   "interests": [
    {
      "name": "Information Technology",
      "keywords": [
        "Big Data",
        "Cloud Computing",
        "Internet of Things",
        "Social Media",
        "Mobile",
        "Artificial Learning",
        "Blockchain"
      ]
    },
    {
      "name": "Chemistry",
      "keywords": [
       "Thermodynamics",
        "Electrochemistry",
        "Mathematics",
        "Physics"
      ]
    },
    {
      "name": "Math",
      "keywords": [
        "Arithmetic",
        "Algebra",
        "Geometry",
        "Trigonometry",
        "Calculus I, II"
      ]
    },
    {
      "name": "Japanese",
      "keywords": [
       "N3",
        "Intermediate",
        "language",
        "culture"
      ]
    },
]
  {
  "skills": [
    {
      "name": "Languages & Frameworks",
      "level": "",
      "keywords": [
        "HTML",
        "CSS"
      ]
    },
    {
      "name": "Toolsets/OS",
      "level": "",
      "keywords": [
        "MacOS",
        "WindowsOS",
        "Microsoft Office",
        "Google Workspace",
        "Git/GitHub", 
      ]
    }
  ],
  "education": [
    {
      "institution": "University of Hawaii, Honolulu, HI",
      "area": "Management Information Systems (expected Spring, 2024)",
      "studyType": "B.S.",
      "startDate": "2022-01-10",
      "endDate": "Present",
      "gpa": "",
      "courses": [
      ]
    },
     {
      "institution": "Leeward Community College, Pearl City, HI",
      "area": "Assoiciates in Exploratory Business",
      "studyType": "B.S.",
      "startDate": "2018-08-01",
      "endDate": "2021-12-17",
      "gpa": "",
      "courses": [
        "Digital Tools for Info World",
        "Discrete Math",
        "Intro to Accounting I, II",
        "Principles of Microeconomics",
        "Principles of Macroeconomics",
        "WI - Business Writing",
        "Legal Environment of Business"
      ]
    }
  ],
  "work": [
    {
      "company": "Leeward Community College Information Technology Services",
      "position": "Help Desk Assistant",
      "website": "www2.leeward.hawaii.edu/itg/helpdesk",
      "startDate": "2021-08-01",
      "endDate": "Present",
      "summary": "",
      "highlights": [
        "Troubleshoot software, hardware and networking issues over the phone",
        "Answer phone and email responses to the ITS Help Desk"
      ]
    },
    {
      "company": "Gyu-Kaku Japanese BBQ Restaurant",
      "position": "Server",
      "website": "www.gyu-kaku.com",
      "startDate": "2018-05-31",
      "endDate": "Present",
      "summary": "",
      "highlights": [
        "Take care of guests through great service to ensure enjoyment in overall dining experience",
        "Work as a team to efficiently deliver food and drinks in a timely manner",
        "Ability to complete multiple tasks with attentiveness to guests’ needs in a busy work environment"
      ]
    },
    {
      "company": "Zara",
      "position": "Sales Associate",
      "website": "www.zara.com",
      "startDate": "2018-03-18",
      "endDate": "Present",
      "summary": "",
      "highlights": [
        "Assess customer needs to provide proper assistance",
        "Contribute to team’s daily goals",
        "Handle payments, issue receipts, process returns",
        "Sales, Stock & RFID Technology, Register POS Systems, and Visual Coordination"
      ]
    }
  ],
  "references": [
    {
      "name": "Available upon request",
      "reference": ""
    }
  ]
}
